odoo/addons/l10n_br_coa_complete/README.rst
odoo/addons/l10n_br_coa_complete/__init__.py
odoo/addons/l10n_br_coa_complete/__manifest__.py
odoo/addons/l10n_br_coa_complete/hooks.py
odoo/addons/l10n_br_coa_complete/data/account.account.template.csv
odoo/addons/l10n_br_coa_complete/data/account_fiscal_position_template.xml
odoo/addons/l10n_br_coa_complete/data/account_group.xml
odoo/addons/l10n_br_coa_complete/data/l10n_br_coa.account.tax.group.account.template.csv
odoo/addons/l10n_br_coa_complete/data/l10n_br_coa_complete_template.xml
odoo/addons/l10n_br_coa_complete/data/l10n_br_coa_complete_template_post.xml
odoo/addons/l10n_br_coa_complete/i18n/l10n_br_coa_complete.pot
odoo/addons/l10n_br_coa_complete/readme/CONFIGURE.rst
odoo/addons/l10n_br_coa_complete/readme/CONTRIBUTORS.rst
odoo/addons/l10n_br_coa_complete/readme/DESCRIPTION.rst
odoo/addons/l10n_br_coa_complete/readme/INSTALL.rst
odoo/addons/l10n_br_coa_complete/readme/ROADMAP.rst
odoo/addons/l10n_br_coa_complete/readme/USAGE.rst
odoo/addons/l10n_br_coa_complete/static/description/banner.png
odoo/addons/l10n_br_coa_complete/static/description/icon.png
odoo/addons/l10n_br_coa_complete/static/description/index.html
odoo/addons/l10n_br_coa_complete/tests/__init__.py
odoo/addons/l10n_br_coa_complete/tests/test_l10n_br_coa_complete.py
odoo12_addon_l10n_br_coa_complete-12.0.2.0.1.dist-info/METADATA
odoo12_addon_l10n_br_coa_complete-12.0.2.0.1.dist-info/WHEEL
odoo12_addon_l10n_br_coa_complete-12.0.2.0.1.dist-info/top_level.txt
odoo12_addon_l10n_br_coa_complete-12.0.2.0.1.dist-info/RECORD
