Metadata-Version: 2.1
Name: odoo12-addon-l10n-br-coa-complete
Version: 12.0.2.0.1
Summary: Plano de Contas Completo para empresas Simples, Presumido, Real, SA, Consolidação
Home-page: https://github.com/OCA/l10n-brazil
Author: Escodoo, Odoo Community Association (OCA)
Author-email: support@odoo-community.org
License: AGPL-3
Platform: UNKNOWN
Classifier: Programming Language :: Python
Classifier: Framework :: Odoo
Classifier: Framework :: Odoo :: 12.0
Classifier: License :: OSI Approved :: GNU Affero General Public License v3
Requires-Python: >=3.5
Requires-Dist: odoo12-addon-l10n-br-coa
Requires-Dist: odoo (<12.1dev,>=12.0a)
